certihound/__init__.py
certihound/cli.py
certihound/collector.py
certihound/config.py
certihound/exporter.py
certihound/py.typed
certihound/acl/__init__.py
certihound/acl/parser.py
certihound/acl/resolver.py
certihound/acl/rights.py
certihound/adapters/__init__.py
certihound/adapters/impacket_adapter.py
certihound/detection/__init__.py
certihound/detection/esc1.py
certihound/detection/esc10.py
certihound/detection/esc13.py
certihound/detection/esc3.py
certihound/detection/esc4.py
certihound/detection/esc6.py
certihound/detection/esc9.py
certihound/detection/goldencert.py
certihound/ldap/__init__.py
certihound/ldap/connection.py
certihound/ldap/parsers.py
certihound/ldap/queries.py
certihound/objects/__init__.py
certihound/objects/aiaca.py
certihound/objects/certtemplate.py
certihound/objects/enterpriseca.py
certihound/objects/ntauthstore.py
certihound/objects/rootca.py
certihound/output/__init__.py
certihound/output/bloodhound.py
certihound/output/edges.py
certihound/output/nodes.py
certihound/output/writer.py
certihound/utils/__init__.py
certihound/utils/convert.py
certihound/utils/crypto.py
certihound/utils/time.py
certihound-0.1.1.dist-info/licenses/LICENSE
certihound-0.1.1.dist-info/METADATA
certihound-0.1.1.dist-info/WHEEL
certihound-0.1.1.dist-info/entry_points.txt
certihound-0.1.1.dist-info/top_level.txt
certihound-0.1.1.dist-info/RECORD
