Metadata-Version: 2.4
Name: certihound
Version: 0.1.1
Summary: Linux-native AD CS collector library for BloodHound CE - enumerate ADCS and export to BloodHound format
Author: CertiHound Contributors
License: MIT
Project-URL: Homepage, https://github.com/0x0Trace/Certihound
Project-URL: Documentation, https://github.com/0x0Trace/Certihound#readme
Project-URL: Repository, https://github.com/0x0Trace/Certihound.git
Project-URL: Issues, https://github.com/0x0Trace/Certihound/issues
Keywords: bloodhound,bloodhound-ce,adcs,active-directory,certificate-services,security,pentesting,red-team,enumeration,ldap,netexec
Classifier: Development Status :: 3 - Alpha
Classifier: Environment :: Console
Classifier: Intended Audience :: Information Technology
Classifier: Intended Audience :: System Administrators
Classifier: License :: OSI Approved :: MIT License
Classifier: Operating System :: POSIX :: Linux
Classifier: Programming Language :: Python :: 3
Classifier: Programming Language :: Python :: 3.10
Classifier: Programming Language :: Python :: 3.11
Classifier: Programming Language :: Python :: 3.12
Classifier: Programming Language :: Python :: 3.13
Classifier: Topic :: Security
Requires-Python: >=3.10
License-File: LICENSE
Requires-Dist: ldap3>=2.9.1
Requires-Dist: impacket>=0.11.0
Requires-Dist: cryptography>=41.0.0
Requires-Dist: pydantic>=2.0
Requires-Dist: click>=8.1.0
Requires-Dist: rich>=13.0.0
Provides-Extra: dev
Requires-Dist: pytest>=7.0.0; extra == "dev"
Requires-Dist: pytest-cov>=4.0.0; extra == "dev"
Requires-Dist: black>=23.0.0; extra == "dev"
Requires-Dist: ruff>=0.1.0; extra == "dev"
Requires-Dist: mypy>=1.0.0; extra == "dev"
Dynamic: license-file
